pyearcal/__init__.py
pyearcal/cli.py
pyearcal/flickr_downloader.py
pyearcal/font_loader.py
pyearcal/image_sources.py
pyearcal/year_calendar.py
pyearcal/l10n/__init__.py
pyearcal/l10n/czech.py
pyearcal/l10n/default.py
pyearcal/l10n/italian.py
pyearcal/l10n/slovak.py
pyearcal-2025.12.0.dist-info/licenses/LICENSE
pyearcal-2025.12.0.dist-info/METADATA
pyearcal-2025.12.0.dist-info/WHEEL
pyearcal-2025.12.0.dist-info/entry_points.txt
pyearcal-2025.12.0.dist-info/top_level.txt
pyearcal-2025.12.0.dist-info/RECORD
