Metadata-Version: 2.4
Name: pyearcal
Version: 2025.12.0
Summary: Year calendar creation in Python
Author-email: Jan Pipek <jan.pipek@gmail.com>
License: The MIT License (MIT)
Requires-Python: <3.15,>=3.11
License-File: LICENSE
Requires-Dist: reportlab
Requires-Dist: matplotlib
Requires-Dist: pillow
Requires-Dist: python-dateutil
Requires-Dist: click
Requires-Dist: fonttools
Provides-Extra: flickr
Requires-Dist: beautifulsoup4; extra == "flickr"
Requires-Dist: requests; extra == "flickr"
Dynamic: license-file
